SinglyLinkedList.py
singlylinkedlist-1.1.dist-info/WHEEL
singlylinkedlist-1.1.dist-info/METADATA
singlylinkedlist-1.1.dist-info/RECORD
