Metadata-Version: 2.1
Name: singlylinkedlist
Version: 1.1
Summary: List(*elements)
Author: semenchuk Community
Author-email: hootuk@yandex.ru
Requires-Python: >=3,<4
Classifier: Programming Language :: Python :: 3
Classifier: Programming Language :: Python :: 3.4
Classifier: Programming Language :: Python :: 3.5
Classifier: Programming Language :: Python :: 3.6
Classifier: Programming Language :: Python :: 3.7
Classifier: Programming Language :: Python :: 3.8
Classifier: Programming Language :: Python :: 3.9
